<?xml version="1.0" encoding="UTF-8" standalone="yes"?>
<document>
  <enww>
    <tagline>U kunt nu overal en altijd afdrukken met uw mobiele telefoon, laptop of een ander mobiel apparaat.</tagline>
    <messageLine>Alleen voor printers met een netwerkverbinding.</messageLine>
    <getStarted>De ePrint-functionaliteit moet worden gedownload.</getStarted>
    <urlLine>Meer online informatie op:</urlLine>
    <anchorHref>http://www.hp.com/go/eprint</anchorHref>
    <finePrint>Een printer met een internetverbinding is vereist. Werkt met elk apparaat dat internet en e-mail ondersteunt. Voor online informatie:</finePrint>
  </enww>
</document>